async_fivem/__init__.py
async_fivem/client.py
async_fivem/exceptions.py
async_fivem/models.py
fivem.py-1.0.5.dist-info/METADATA
fivem.py-1.0.5.dist-info/WHEEL
fivem.py-1.0.5.dist-info/top_level.txt
fivem.py-1.0.5.dist-info/RECORD
