Metadata-Version: 2.1
Name: fivem.py
Version: 1.0.5
Summary: FiveM API Wrapper
Home-page: https://github.com/pypi/
Author: github.com/Wiper-R
Author-email: rshivang12345@gmail.com
License: UNKNOWN
Platform: UNKNOWN
Classifier: Programming Language :: Python :: 3
Classifier: License :: OSI Approved :: MIT License
Classifier: Operating System :: OS Independent
Requires-Python: >=3.8
